{
  "id": "508",
  "meditationType": "MEDITATE_WITH_TRAINER",
  "title": "Saint Martin clicks-and-mortar",
  "subTitle": "Home Loan Account Switzerland withdrawal",
  "description": "experiences Pines Associate",
  "durationOfMeditationClip": 739,
  "tag": "Utah",
  "rating": 234.19392,
  "likes": 126,
  "audioUrl": "card",
  "imageUrl": "withdrawal",
  "durationFile": {
    "id": "162",
    "durationInSeconds": 556,
    "imageURL": "Via Future",
    "selectedImageURL": "Lead deposit Bridge"
  },
  "purposeFile": {
    "id": "621",
    "purpose": "Ferry plug-and-play contextually-based",
    "imageURL": "orchestrate",
    "withoutBorderImageUrl": "Oregon Small Rubber Hat"
  },
  "thumbnailImgUrl": "Heights Assistant",
  "audioUrlV2": "Tenge",
  "durationOfInstructionClip": 487,
  "backgroundImageUrl": "azure",
  "tags": [
    {
      "id": "328",
      "name": "{{ faker.name.last_name }}"
    },
    {
      "id": "236",
      "name": "{{ faker.name.last_name }}"
    }
  ],
  "tagIds": [
    "972",
    "110"
  ],
  "attribute": "AI",
  "meditationCategory": "CLEANING_MEDITATION"
}